simplebrainviewer/__init__.py
simplebrainviewer/core.py
simplebrainviewer/scripts/__init__.py
simplebrainviewer/scripts/sbv.py
simplebrainviewer-0.3.2.dist-info/LICENSE
simplebrainviewer-0.3.2.dist-info/METADATA
simplebrainviewer-0.3.2.dist-info/WHEEL
simplebrainviewer-0.3.2.dist-info/entry_points.txt
simplebrainviewer-0.3.2.dist-info/top_level.txt
simplebrainviewer-0.3.2.dist-info/zip-safe
simplebrainviewer-0.3.2.dist-info/RECORD
