Metadata-Version: 2.1
Name: simplebrainviewer
Version: 0.3.2
Summary: A simple brain viewer using matplotlib
Author-email: Andrew Van <vanandrew@wustl.edu>
License: MIT License
Project-URL: github, https://github.com/vanandrew/Simplebrainviewer
Keywords: neuroscience,neuroimaging
Classifier: License :: OSI Approved :: MIT License
Classifier: Programming Language :: Python :: 3
Classifier: Programming Language :: C++
Classifier: Topic :: Scientific/Engineering :: Image Processing
Requires-Python: >=3.7
License-File: LICENSE
Requires-Dist: nibabel (>=3.2.2)
Requires-Dist: matplotlib (>=3.5.1)
Provides-Extra: dev
Requires-Dist: black (>=21.0) ; extra == 'dev'
